birth_teller/__init__.py
birth_teller/cli.py
birth_teller/core.py
birth_teller-0.2.1.dist-info/licenses/LICENSE
birth_teller-0.2.1.dist-info/METADATA
birth_teller-0.2.1.dist-info/WHEEL
birth_teller-0.2.1.dist-info/entry_points.txt
birth_teller-0.2.1.dist-info/top_level.txt
birth_teller-0.2.1.dist-info/RECORD
