Metadata-Version: 2.4
Name: birth_teller
Version: 0.2.1
Summary: A Python package to calculate birthdays and zodiac info
Author-email: Emran Hossain Sagor <imrans4gor@gmail.com>
License: GPL-3.0
Project-URL: Repository, https://github.com/exeebit/birth-teller
Project-URL: Issues, https://github.com/exeebit/birth-teller/issues
Project-URL: Changelog, https://github.com/exeebit/birth-teller/blob/main/CHANGELOG.md
Keywords: birthday,day,birthday,week day
Classifier: Programming Language :: Python :: 3
Classifier: License :: OSI Approved :: GNU General Public License v3 (GPLv3)
Classifier: Operating System :: OS Independent
Requires-Python: >=3.0
License-File: LICENSE
Dynamic: license-file
